[
  {
    "name": "Coffee Beans",
    "cost": 2.0,
    "unit": "KILOS"
  },
  {
    "name": "Milk",
    "cost": 1.5,
    "unit": "LITERS"
  },
  {
    "name": "Sugar",
    "cost": 2.0,
    "unit": "KILOS"
  },
  {
    "name": "Chocolate",
    "cost": 0.002,
    "unit": "GRAMS"
  },
  {
    "name": "Flour",
    "cost": 2.0,
    "unit": "KILOS"
  },
  {
    "name": "Egg",
    "cost": 0.25,
    "unit": "OUNCES"
  },
  {
    "name": "Orange Juice",
    "cost": 1.5,
    "unit": "LITERS"
  },
  {
    "name": "Lemon",
    "cost": 0.002,
    "unit": "GRAMS"
  },
  {
    "name": "Cream Cheese",
    "cost": 4.5,
    "unit": "POUNDS"
  },
  {
    "name": "Apple",
    "cost": 0.25,
    "unit": "OUNCES"
  },
  {
    "name": "Butter",
    "cost": 4.5,
    "unit": "POUNDS"
  },
  {
    "name": "Water",
    "cost": 1.5,
    "unit": "LITERS"
  },
  {
    "name": "Honey",
    "cost": 0.002,
    "unit": "GRAMS"
  },
  {
    "name": "Vanilla Extract",
    "cost": 2.0,
    "unit": "KILOS"
  },
  {
    "name": "Cinnamon",
    "cost": 0.002,
    "unit": "GRAMS"
  },
  {
    "name": "Brown Sugar",
    "cost": 2.0,
    "unit": "KILOS"
  },
  {
    "name": "Baking Powder",
    "cost": 0.002,
    "unit": "GRAMS"
  },
  {
    "name": "Whipping Cream",
    "cost": 1.5,
    "unit": "LITERS"
  },
  {
    "name": "Salt",
    "cost": 0.002,
    "unit": "GRAMS"
  },
  {
    "name": "Bread",
    "cost": 0.002,
    "unit": "GRAMS"
  }
]
